[{"time":1585264921110,"x":389,"y":199,"type":"mousemove"},{"time":1585264921177,"x":369,"y":206,"type":"mousemove"},{"time":1585264921206,"x":355,"y":201,"type":"mousemove"},{"time":1585264921238,"x":337,"y":185,"type":"mousemove"},{"time":1585264921254,"x":331,"y":172,"type":"mousemove"},{"time":1585264921283,"x":328,"y":155,"type":"mousemove"},{"time":1585264921288,"x":328,"y":151,"type":"mousemove"},{"time":1585264921313,"x":335,"y":141,"type":"mousemove"},{"time":1585264921325,"x":338,"y":137,"type":"mousemove"},{"time":1585264921336,"x":350,"y":131,"type":"mousemove"},{"time":1585264921343,"x":371,"y":128,"type":"mousemove"},{"time":1585264921357,"x":374,"y":127,"type":"mousemove"},{"time":1585264921357,"x":378,"y":127,"type":"mousemove"},{"time":1585264921365,"x":413,"y":127,"type":"mousemove"},{"time":1585264921373,"x":455,"y":131,"type":"mousemove"},{"time":1585264921386,"x":488,"y":139,"type":"mousemove"},{"time":1585264921388,"x":514,"y":145,"type":"mousemove"},{"time":1585264921397,"x":536,"y":155,"type":"mousemove"},{"time":1585264921408,"x":549,"y":164,"type":"mousemove"},{"time":1585264921419,"x":558,"y":172,"type":"mousemove"},{"time":1585264921481,"x":554,"y":243,"type":"mousemove"},{"time":1585264921488,"x":547,"y":251,"type":"mousemove"},{"time":1585264921506,"x":541,"y":258,"type":"mousemove"},{"time":1585264921509,"x":530,"y":264,"type":"mousemove"},{"time":1585264921510,"x":520,"y":268,"type":"mousemove"},{"time":1585264921522,"x":506,"y":273,"type":"mousemove"},{"time":1585264921532,"x":485,"y":277,"type":"mousemove"},{"time":1585264921541,"x":465,"y":279,"type":"mousemove"},{"time":1585264921542,"x":444,"y":279,"type":"mousemove"},{"time":1585264921552,"x":423,"y":279,"type":"mousemove"},{"time":1585264921562,"x":402,"y":276,"type":"mousemove"},{"time":1585264921571,"x":383,"y":272,"type":"mousemove"},{"time":1585264921574,"x":366,"y":267,"type":"mousemove"},{"time":1585264921590,"x":336,"y":250,"type":"mousemove"},{"time":1585264921601,"x":323,"y":240,"type":"mousemove"},{"time":1585264921608,"x":311,"y":227,"type":"mousemove"},{"time":1585264921624,"x":300,"y":207,"type":"mousemove"},{"time":1585264921636,"x":298,"y":202,"type":"mousemove"},{"time":1585264921649,"x":298,"y":195,"type":"mousemove"},{"time":1585264921659,"x":300,"y":189,"type":"mousemove"},{"time":1585264921662,"x":306,"y":182,"type":"mousemove"},{"time":1585264921677,"x":309,"y":180,"type":"mousemove"},{"time":1585264921700,"x":358,"y":165,"type":"mousemove"},{"time":1585264921712,"x":417,"y":160,"type":"mousemove"},{"time":1585264921721,"x":448,"y":161,"type":"mousemove"},{"time":1585264921730,"x":481,"y":169,"type":"mousemove"},{"time":1585264921739,"x":507,"y":176,"type":"mousemove"},{"time":1585264921752,"x":559,"y":204,"type":"mousemove"},{"time":1585264921759,"x":579,"y":221,"type":"mousemove"},{"time":1585264921776,"x":594,"y":244,"type":"mousemove"},{"time":1585264921796,"x":596,"y":264,"type":"mousemove"},{"time":1585264921799,"x":588,"y":278,"type":"mousemove"},{"time":1585264921812,"x":576,"y":293,"type":"mousemove"},{"time":1585264921813,"x":556,"y":309,"type":"mousemove"},{"time":1585264921828,"x":534,"y":322,"type":"mousemove"},{"time":1585264921846,"x":455,"y":348,"type":"mousemove"},{"time":1585264921865,"x":413,"y":349,"type":"mousemove"},{"time":1585264921883,"x":378,"y":341,"type":"mousemove"},{"time":1585264921898,"x":351,"y":328,"type":"mousemove"},{"time":1585264921910,"x":340,"y":321,"type":"mousemove"},{"time":1585264921926,"x":323,"y":304,"type":"mousemove"},{"time":1585264921926,"x":318,"y":292,"type":"mousemove"},{"time":1585264921942,"x":314,"y":280,"type":"mousemove"},{"time":1585264921942,"x":312,"y":267,"type":"mousemove"},{"time":1585264921961,"x":311,"y":242,"type":"mousemove"},{"time":1585264921971,"x":314,"y":235,"type":"mousemove"},{"time":1585264921986,"x":320,"y":227,"type":"mousemove"},{"time":1585264921998,"x":326,"y":224,"type":"mousemove"},{"time":1585264922014,"x":348,"y":219,"type":"mousemove"},{"time":1585264922026,"x":372,"y":218,"type":"mousemove"},{"time":1585264922038,"x":424,"y":221,"type":"mousemove"},{"time":1585264922053,"x":476,"y":238,"type":"mousemove"},{"time":1585264922066,"x":494,"y":245,"type":"mousemove"},{"time":1585264922080,"x":514,"y":260,"type":"mousemove"},{"time":1585264922091,"x":519,"y":264,"type":"mousemove"},{"time":1585264922106,"x":521,"y":272,"type":"mousemove"},{"time":1585264922117,"x":520,"y":282,"type":"mousemove"},{"time":1585264922130,"x":516,"y":288,"type":"mousemove"},{"time":1585264922144,"x":509,"y":295,"type":"mousemove"},{"time":1585264922145,"x":499,"y":303,"type":"mousemove"},{"time":1585264922157,"x":488,"y":310,"type":"mousemove"},{"time":1585264922172,"x":450,"y":324,"type":"mousemove"},{"time":1585264922186,"x":414,"y":330,"type":"mousemove"},{"time":1585264922198,"x":381,"y":328,"type":"mousemove"},{"time":1585264922212,"x":363,"y":319,"type":"mousemove"},{"time":1585264922213,"x":349,"y":313,"type":"mousemove"},{"time":1585264922226,"x":333,"y":305,"type":"mousemove"},{"time":1585264922240,"x":307,"y":283,"type":"mousemove"},{"time":1585264922255,"x":293,"y":263,"type":"mousemove"},{"time":1585264922269,"x":288,"y":243,"type":"mousemove"},{"time":1585264922284,"x":288,"y":230,"type":"mousemove"},{"time":1585264922285,"x":290,"y":221,"type":"mousemove"},{"time":1585264922298,"x":294,"y":213,"type":"mousemove"},{"time":1585264922311,"x":300,"y":207,"type":"mousemove"},{"time":1585264922332,"x":348,"y":184,"type":"mousemove"},{"time":1585264922335,"x":374,"y":178,"type":"mousemove"},{"time":1585264922353,"x":389,"y":178,"type":"mousemove"},{"time":1585264922367,"x":454,"y":193,"type":"mousemove"},{"time":1585264922380,"x":479,"y":201,"type":"mousemove"},{"time":1585264922394,"x":514,"y":226,"type":"mousemove"},{"time":1585264922406,"x":524,"y":249,"type":"mousemove"},{"time":1585264922423,"x":520,"y":274,"type":"mousemove"},{"time":1585264922436,"x":512,"y":285,"type":"mousemove"},{"time":1585264922437,"x":501,"y":295,"type":"mousemove"},{"time":1585264922449,"x":476,"y":304,"type":"mousemove"},{"time":1585264922459,"x":449,"y":315,"type":"mousemove"},{"time":1585264922474,"x":381,"y":320,"type":"mousemove"},{"time":1585264922490,"x":315,"y":308,"type":"mousemove"},{"time":1585264922501,"x":285,"y":292,"type":"mousemove"},{"time":1585264922516,"x":273,"y":285,"type":"mousemove"},{"time":1585264922527,"x":262,"y":271,"type":"mousemove"},{"time":1585264922542,"x":259,"y":253,"type":"mousemove"},{"time":1585264922552,"x":260,"y":245,"type":"mousemove"},{"time":1585264922567,"x":266,"y":222,"type":"mousemove"},{"time":1585264922578,"x":274,"y":210,"type":"mousemove"},{"time":1585264922590,"x":293,"y":194,"type":"mousemove"},{"time":1585264922609,"x":336,"y":180,"type":"mousemove"},{"time":1585264922619,"x":361,"y":177,"type":"mousemove"},{"time":1585264922629,"x":394,"y":175,"type":"mousemove"},{"time":1585264922640,"x":459,"y":178,"type":"mousemove"},{"time":1585264922648,"x":491,"y":181,"type":"mousemove"},{"time":1585264922657,"x":517,"y":189,"type":"mousemove"},{"time":1585264922666,"x":531,"y":195,"type":"mousemove"},{"time":1585264922676,"x":545,"y":204,"type":"mousemove"},{"time":1585264922677,"x":552,"y":210,"type":"mousemove"},{"time":1585264922688,"x":555,"y":215,"type":"mousemove"},{"time":1585264922697,"x":555,"y":219,"type":"mousemove"},{"time":1585264922713,"x":553,"y":226,"type":"mousemove"},{"time":1585264922724,"x":547,"y":232,"type":"mousemove"},{"time":1585264922724,"x":540,"y":236,"type":"mousemove"},{"time":1585264922741,"x":521,"y":243,"type":"mousemove"},{"time":1585264922759,"x":483,"y":250,"type":"mousemove"},{"time":1585264922769,"x":463,"y":252,"type":"mousemove"},{"time":1585264922781,"x":454,"y":252,"type":"mousemove"},{"time":1585264922788,"x":437,"y":252,"type":"mousemove"},{"time":1585264922788,"x":430,"y":252,"type":"mousemove"},{"time":1585264922797,"x":420,"y":251,"type":"mousemove"},{"time":1585264922808,"x":413,"y":247,"type":"mousemove"},{"time":1585264922816,"x":407,"y":245,"type":"mousemove"},{"time":1585264922826,"x":404,"y":242,"type":"mousemove"},{"time":1585264922837,"x":400,"y":235,"type":"mousemove"},{"time":1585264922860,"x":399,"y":232,"type":"mousemove"},{"time":1585264922860,"x":398,"y":227,"type":"mousemove"},{"time":1585264922872,"x":398,"y":222,"type":"mousemove"},{"time":1585264922884,"x":398,"y":217,"type":"mousemove"},{"time":1585264922903,"x":404,"y":208,"type":"mousemove"},{"time":1585264922909,"x":409,"y":204,"type":"mousemove"},{"time":1585264922932,"x":428,"y":197,"type":"mousemove"},{"time":1585264922942,"x":463,"y":195,"type":"mousemove"},{"time":1585264922952,"x":483,"y":202,"type":"mousemove"},{"time":1585264922962,"x":507,"y":212,"type":"mousemove"},{"time":1585264922976,"x":549,"y":243,"type":"mousemove"},{"time":1585264922990,"x":573,"y":276,"type":"mousemove"},{"time":1585264923000,"x":579,"y":289,"type":"mousemove"},{"time":1585264923014,"x":579,"y":311,"type":"mousemove"},{"time":1585264923025,"x":575,"y":321,"type":"mousemove"},{"time":1585264923036,"x":569,"y":329,"type":"mousemove"},{"time":1585264923051,"x":552,"y":341,"type":"mousemove"},{"time":1585264923058,"x":531,"y":345,"type":"mousemove"},{"time":1585264923076,"x":476,"y":342,"type":"mousemove"},{"time":1585264923089,"x":408,"y":325,"type":"mousemove"},{"time":1585264923100,"x":377,"y":313,"type":"mousemove"},{"time":1585264923111,"x":330,"y":285,"type":"mousemove"},{"time":1585264923128,"x":321,"y":277,"type":"mousemove"},{"time":1585264923158,"x":321,"y":264,"type":"mousemove"},{"time":1585264923167,"x":325,"y":257,"type":"mousemove"},{"time":1585264923179,"x":328,"y":253,"type":"mousemove"},{"time":1585264923189,"x":342,"y":238,"type":"mousemove"},{"time":1585264923199,"x":352,"y":231,"type":"mousemove"},{"time":1585264923209,"x":359,"y":228,"type":"mousemove"},{"time":1585264923219,"x":370,"y":223,"type":"mousemove"},{"time":1585264923231,"x":389,"y":220,"type":"mousemove"},{"time":1585264923243,"x":408,"y":220,"type":"mousemove"},{"time":1585264923253,"x":429,"y":222,"type":"mousemove"},{"time":1585264923271,"x":476,"y":242,"type":"mousemove"},{"time":1585264923283,"x":485,"y":250,"type":"mousemove"},{"time":1585264923284,"x":491,"y":263,"type":"mousemove"},{"time":1585264923294,"x":493,"y":272,"type":"mousemove"},{"time":1585264923305,"x":493,"y":282,"type":"mousemove"},{"time":1585264923316,"x":493,"y":290,"type":"mousemove"},{"time":1585264923328,"x":480,"y":312,"type":"mousemove"},{"time":1585264923349,"x":463,"y":327,"type":"mousemove"},{"time":1585264923361,"x":448,"y":333,"type":"mousemove"},{"time":1585264923375,"x":428,"y":337,"type":"mousemove"},{"time":1585264923377,"x":405,"y":340,"type":"mousemove"},{"time":1585264923389,"x":377,"y":339,"type":"mousemove"},{"time":1585264923402,"x":351,"y":337,"type":"mousemove"},{"time":1585264923423,"x":294,"y":314,"type":"mousemove"},{"time":1585264923439,"x":288,"y":309,"type":"mousemove"},{"time":1585264923453,"x":286,"y":303,"type":"mousemove"},{"time":1585264923467,"x":286,"y":296,"type":"mousemove"},{"time":1585264923484,"x":290,"y":282,"type":"mousemove"},{"time":1585264923485,"x":296,"y":272,"type":"mousemove"},{"time":1585264923496,"x":305,"y":262,"type":"mousemove"},{"time":1585264923507,"x":314,"y":253,"type":"mousemove"},{"time":1585264923520,"x":348,"y":235,"type":"mousemove"},{"time":1585264923541,"x":359,"y":232,"type":"mousemove"},{"time":1585264923556,"x":410,"y":225,"type":"mousemove"},{"time":1585264923568,"x":453,"y":226,"type":"mousemove"},{"time":1585264923580,"x":474,"y":233,"type":"mousemove"},{"time":1585264923581,"x":489,"y":242,"type":"mousemove"},{"time":1585264923594,"x":496,"y":251,"type":"mousemove"},{"time":1585264923606,"x":507,"y":272,"type":"mousemove"},{"time":1585264923615,"x":509,"y":283,"type":"mousemove"},{"time":1585264923626,"x":508,"y":297,"type":"mousemove"},{"time":1585264923637,"x":500,"y":313,"type":"mousemove"},{"time":1585264923647,"x":493,"y":321,"type":"mousemove"},{"time":1585264923659,"x":486,"y":326,"type":"mousemove"},{"time":1585264923671,"x":462,"y":334,"type":"mousemove"},{"time":1585264923680,"x":447,"y":336,"type":"mousemove"},{"time":1585264923704,"x":402,"y":335,"type":"mousemove"},{"time":1585264923717,"x":381,"y":327,"type":"mousemove"},{"time":1585264923729,"x":375,"y":323,"type":"mousemove"},{"time":1585264923739,"x":372,"y":319,"type":"mousemove"},{"time":1585264923750,"x":365,"y":309,"type":"mousemove"},{"time":1585264923762,"x":364,"y":304,"type":"mousemove"},{"time":1585264923774,"x":364,"y":293,"type":"mousemove"},{"time":1585264923786,"x":364,"y":288,"type":"mousemove"},{"time":1585264923806,"x":384,"y":266,"type":"mousemove"},{"time":1585264923828,"x":421,"y":251,"type":"mousemove"},{"time":1585264923831,"x":440,"y":247,"type":"mousemove"},{"time":1585264923851,"x":458,"y":244,"type":"mousemove"},{"time":1585264923867,"x":503,"y":248,"type":"mousemove"},{"time":1585264923881,"x":561,"y":271,"type":"mousemove"},{"time":1585264923899,"x":595,"y":294,"type":"mousemove"},{"time":1585264923915,"x":603,"y":308,"type":"mousemove"},{"time":1585264923932,"x":603,"y":317,"type":"mousemove"},{"time":1585264923933,"x":597,"y":322,"type":"mousemove"},{"time":1585264923948,"x":587,"y":327,"type":"mousemove"},{"time":1585264923949,"x":574,"y":329,"type":"mousemove"},{"time":1585264923966,"x":550,"y":332,"type":"mousemove"},{"time":1585264923981,"x":508,"y":330,"type":"mousemove"},{"time":1585264923983,"x":477,"y":325,"type":"mousemove"},{"time":1585264924012,"x":472,"y":323,"type":"mousemove"},{"time":1585264924014,"x":460,"y":316,"type":"mousemove"},{"time":1585264924042,"x":452,"y":310,"type":"mousemove"},{"time":1585264924045,"x":452,"y":310,"type":"mousemove"},{"time":1585264924080,"x":454,"y":306,"type":"mousemove"},{"time":1585265623449,"x":569,"y":471,"type":"mousemove"},{"time":1585265623497,"x":544,"y":379,"type":"mousemove"},{"time":1585265623498,"x":544,"y":379,"type":"mousemove"},{"time":1585265623534,"x":544,"y":380,"type":"mousemove"},{"time":1585265623622,"x":545,"y":380,"type":"mousemove"},{"time":1585265623667,"x":545,"y":380,"type":"mousemove"}]